samspecialfuncs-0.0.5.dist-info/RECORD
samspecialfuncs-0.0.5.dist-info/WHEEL
samspecialfuncs-0.0.5.dist-info/LICENSE
samspecialfuncs-0.0.5.dist-info/METADATA
samspecialfuncs-0.0.5.dist-info/top_level.txt
samspecialfuncs/bessellike/nufuncs.cpython-37m-x86_64-linux-gnu.so
