Metadata-Version: 2.1
Name: samspecialfuncs
Version: 0.0.5
Summary: Special functions that Sam needs
Home-page: https://github.com/samueljmcameron/samspecialfuncs
Author: Sam Cameron
Author-email: samuel.j.m.cameron@gmail.com
License: UNKNOWN
Platform: UNKNOWN
Classifier: Programming Language :: Python :: 3
Classifier: License :: OSI Approved :: GNU General Public License v3 (GPLv3)
Classifier: Operating System :: OS Independent
Requires-Python: >=3.6
Requires-Dist: numpy
